open_pcc_metric/__init__.py
open_pcc_metric/__main__.py
open_pcc_metric/calculator.py
open_pcc_metric/cloud_pair.py
open_pcc_metric/handler.py
open_pcc_metric/logger.py
open_pcc_metric/metric.py
open_pcc_metric/options.py
open_pcc_metric-0.1.2.dist-info/LICENSE
open_pcc_metric-0.1.2.dist-info/METADATA
open_pcc_metric-0.1.2.dist-info/WHEEL
open_pcc_metric-0.1.2.dist-info/RECORD
