Metadata-Version: 2.1
Name: open-pcc-metric
Version: 0.1.2
Summary: 
License: MIT
Author: aapozd
Author-email: aapozdnyakove@gmail.com
Requires-Python: >=3.8.1,<4.0.0
Classifier: License :: OSI Approved :: MIT License
Classifier: Programming Language :: Python :: 3
Classifier: Programming Language :: Python :: 3.9
Classifier: Programming Language :: Python :: 3.10
Classifier: Programming Language :: Python :: 3.11
Classifier: Programming Language :: Python :: 3.12
Requires-Dist: addict (==2.4.0)
Requires-Dist: click (>=8.1.7,<9.0.0)
Requires-Dist: matplotlib (==3.7)
Requires-Dist: numpy (==1.24)
Requires-Dist: open3d (>=0.18.0,<0.19.0)
Requires-Dist: pandas (==2.0)
Requires-Dist: pillow (==10.3.0)
Requires-Dist: pyquaternion (==0.9.9)
Requires-Dist: pyyaml (==6.0.1)
Requires-Dist: scikit-learn (==1.3)
Requires-Dist: tqdm (==4.66.2)
